smmips/__init__.py
smmips/smmips.py
smmips/smmips_libs.py
smmips-1.0.9.dist-info/LICENSE
smmips-1.0.9.dist-info/METADATA
smmips-1.0.9.dist-info/WHEEL
smmips-1.0.9.dist-info/entry_points.txt
smmips-1.0.9.dist-info/top_level.txt
smmips-1.0.9.dist-info/RECORD
