Metadata-Version: 2.1
Name: smmips
Version: 1.0.9
Summary: A package to generate QC metrics for smMIP libraries
Home-page: https://github.com/oicr-gsi/pysmmips
Author: Richard Jovelin
Author-email: richard.jovelin@oicr.on.ca
License: MIT License
Keywords: computational genomics
Platform: UNKNOWN
Classifier: Development Status :: 3 - Alpha
Classifier: Intended Audience :: Science/Research
Classifier: Intended Audience :: Developers
Classifier: License :: OSI Approved :: MIT License
Classifier: Programming Language :: Python :: 3
Classifier: Programming Language :: Python :: 3.6
Classifier: Topic :: Software Development
Classifier: Topic :: Scientific/Engineering
Classifier: Operating System :: POSIX
Classifier: Operating System :: Unix
Classifier: Operating System :: MacOS
Requires-Python: >=3.6
Requires-Dist: regex (>=2020.6.8)
Requires-Dist: pysam (>=0.14.1)
Requires-Dist: biopython (>=1.78)
